{
    "Nouns": [
        {"word": "Dezember", "gender": "m"},
        {"word": "Müller", "gender": "m"},
        {"word": "Nashorn", "gender": "m"},
        {"word": "Tisch", "gender": "m"},
        {"word": "Habitus", "gender": "m"},
        {"word": "Spieler", "gender": "m"},
        {"word": "Hall", "gender": "m"},
        {"word": "Zug", "gender": "m"},
        {"word": "Geheimbund", "gender": "m"},
        {"word": "Durchmarsch", "gender": "m"},
        {"word": "Pol", "gender": "m"},
        {"word": "Handel", "gender": "m"},
        {"word": "Bergarbeiter", "gender": "m"},
        {"word": "Berater", "gender": "m"},
        {"word": "Prozentpunkt", "gender": "m"},
        {"word": "Erstwähler", "gender": "m"},
        {"word": "Träger", "gender": "m"},

        {"word": "Gazelle", "gender": "f"},
        {"word": "Welt", "gender": "f"},
        {"word": "Gabel", "gender": "f"},
        {"word": "Gabe", "gender": "f"},
        {"word": "Habe", "gender": "f"},
        {"word": "Spielbank", "gender": "f"},
        {"word": "Halle", "gender": "f"},
        {"word": "Leuchtschrift", "gender": "f"},
        {"word": "Prostitution", "gender": "f"},
        {"word": "Krippe", "gender": "f"},
        {"word": "Fälscherin", "gender": "f"},
        {"word": "Zahlungsbilanz", "gender": "f"},
        {"word": "Drainage", "gender": "f"},
        {"word": "Einfahrt", "gender": "f"},

        {"word": "Konzept", "gender": "n"},
        {"word": "Auto", "gender": "n"},
        {"word": "Saft", "gender": "n"},
        {"word": "Haar", "gender": "n"},
        {"word": "Hack", "gender": "n"},
        {"word": "Spiel", "gender": "n"},
        {"word": "Bad", "gender": "n"},
        {"word": "Plazet", "gender": "n"},
        {"word": "Höchstgebot", "gender": "n"},
        {"word": "Geräteturnen", "gender": "n"},

        {"word": "Menschen", "gender": "p"},
        {"word": "Häuse", "gender": "p"},
        {"word": "Leute", "gender": "p"},
        {"word": "Kinder", "gender": "p"}
    ]
}
